musong/__init__.py
musong/benchmarks.py
musong/cli.py
musong/detect.py
musong/export.py
musong/helpers.py
musong/hubconf.py
musong/train.py
musong/val.py
musong/classify/__init__.py
musong/classify/predict.py
musong/classify/train.py
musong/classify/val.py
musong/models/__init__.py
musong/models/common.py
musong/models/experimental.py
musong/models/tf.py
musong/models/yolo.py
musong/segment/__init__.py
musong/segment/predict.py
musong/segment/train.py
musong/segment/val.py
musong/utils/__init__.py
musong/utils/activations.py
musong/utils/augmentations.py
musong/utils/autoanchor.py
musong/utils/autobatch.py
musong/utils/aws.py
musong/utils/callbacks.py
musong/utils/dataloaders.py
musong/utils/downloads.py
musong/utils/general.py
musong/utils/loss.py
musong/utils/metrics.py
musong/utils/plots.py
musong/utils/torch_utils.py
musong/utils/triton.py
musong/utils/loggers/__init__.py
musong/utils/loggers/clearml/__init__.py
musong/utils/loggers/clearml/clearml_utils.py
musong/utils/loggers/clearml/hpo.py
musong/utils/loggers/comet/__init__.py
musong/utils/loggers/comet/comet_utils.py
musong/utils/loggers/comet/hpo.py
musong/utils/loggers/neptune/__init__.py
musong/utils/loggers/neptune/neptune_utils.py
musong/utils/loggers/wandb/__init__.py
musong/utils/loggers/wandb/log_dataset.py
musong/utils/loggers/wandb/sweep.py
musong/utils/loggers/wandb/wandb_utils.py
musong/utils/segment/__init__.py
musong/utils/segment/augmentations.py
musong/utils/segment/dataloaders.py
musong/utils/segment/general.py
musong/utils/segment/loss.py
musong/utils/segment/metrics.py
musong/utils/segment/plots.py
musong-0.0.6.dist-info/LICENSE
musong-0.0.6.dist-info/METADATA
musong-0.0.6.dist-info/WHEEL
musong-0.0.6.dist-info/entry_points.txt
musong-0.0.6.dist-info/top_level.txt
musong-0.0.6.dist-info/RECORD
